IbmDeveloperworksQuanbuWenzhangDiyiBufen/README.md
IbmDeveloperworksQuanbuWenzhangDiyiBufen/__init__.py
IbmDeveloperworksQuanbuWenzhangDiyiBufen/__main__.py
IbmDeveloperworksQuanbuWenzhangDiyiBufen/file.epub
IbmDeveloperworksQuanbuWenzhangDiyiBufen/index.html
IbmDeveloperworksQuanbuWenzhangDiyiBufen/css/__init__.py
IbmDeveloperworksQuanbuWenzhangDiyiBufen/css/annotations.css
IbmDeveloperworksQuanbuWenzhangDiyiBufen/css/main.css
IbmDeveloperworksQuanbuWenzhangDiyiBufen/css/normalize.css
IbmDeveloperworksQuanbuWenzhangDiyiBufen/css/popup.css
IbmDeveloperworksQuanbuWenzhangDiyiBufen/font/__init__.py
IbmDeveloperworksQuanbuWenzhangDiyiBufen/font/fontello.eot
IbmDeveloperworksQuanbuWenzhangDiyiBufen/font/fontello.svg
IbmDeveloperworksQuanbuWenzhangDiyiBufen/font/fontello.ttf
IbmDeveloperworksQuanbuWenzhangDiyiBufen/font/fontello.woff
IbmDeveloperworksQuanbuWenzhangDiyiBufen/img/__init__.py
IbmDeveloperworksQuanbuWenzhangDiyiBufen/img/annotator-glyph-sprite.png
IbmDeveloperworksQuanbuWenzhangDiyiBufen/img/annotator-icon-sprite.png
IbmDeveloperworksQuanbuWenzhangDiyiBufen/img/apple-touch-icon.png
IbmDeveloperworksQuanbuWenzhangDiyiBufen/img/cancelfullscreen.png
IbmDeveloperworksQuanbuWenzhangDiyiBufen/img/close.png
IbmDeveloperworksQuanbuWenzhangDiyiBufen/img/fullscreen.png
IbmDeveloperworksQuanbuWenzhangDiyiBufen/img/loader.gif
IbmDeveloperworksQuanbuWenzhangDiyiBufen/img/menu-icon.png
IbmDeveloperworksQuanbuWenzhangDiyiBufen/img/save.png
IbmDeveloperworksQuanbuWenzhangDiyiBufen/img/saved.png
IbmDeveloperworksQuanbuWenzhangDiyiBufen/img/settings-s.png
IbmDeveloperworksQuanbuWenzhangDiyiBufen/img/settings.png
IbmDeveloperworksQuanbuWenzhangDiyiBufen/img/star.png
IbmDeveloperworksQuanbuWenzhangDiyiBufen/js/__init__.py
IbmDeveloperworksQuanbuWenzhangDiyiBufen/js/epub.js
IbmDeveloperworksQuanbuWenzhangDiyiBufen/js/epub.min.js
IbmDeveloperworksQuanbuWenzhangDiyiBufen/js/epub.min.map
IbmDeveloperworksQuanbuWenzhangDiyiBufen/js/hooks.min.js
ibm_developerworks_quanbu_wenzhang_diyi_bufen-2024.3.6.0.dist-info/METADATA
ibm_developerworks_quanbu_wenzhang_diyi_bufen-2024.3.6.0.dist-info/WHEEL
ibm_developerworks_quanbu_wenzhang_diyi_bufen-2024.3.6.0.dist-info/entry_points.txt
ibm_developerworks_quanbu_wenzhang_diyi_bufen-2024.3.6.0.dist-info/top_level.txt
ibm_developerworks_quanbu_wenzhang_diyi_bufen-2024.3.6.0.dist-info/RECORD
